shirah_reader/__init__.py
shirah_reader/__main__.py
shirah_reader-1.0.0.dist-info/METADATA
shirah_reader-1.0.0.dist-info/WHEEL
shirah_reader-1.0.0.dist-info/entry_points.txt
shirah_reader-1.0.0.dist-info/top_level.txt
shirah_reader-1.0.0.dist-info/RECORD
