Metadata-Version: 2.1
Name: shirah-reader
Version: 1.0.0
Summary: UNKNOWN
Home-page: https://github.com/hallicopter/shirah-reader
Author: Hallicopter
Author-email: advait.raykar@gmail.com
License: MIT
Platform: UNKNOWN
Classifier: Programming Language :: Python :: 3
Classifier: Programming Language :: Python :: 3.7
Requires-Dist: EbookLib
Requires-Dist: beautifulsoup4
Requires-Dist: syllables
Requires-Dist: termcolor
